svelte_web_components/__init__.py
svelte_web_components/bundle.py
svelte_web_components/cli.py
svelte_web_components/models.py
svelte_web_components/paths.py
svelte_web_components/server.py
svelte_web_components/sveltefiles.py
svelte_web_components/tools.py
svelte_web_components/workspace.py
svelte_web_components/svelte_app/main.js.jinja2
svelte_web_components/svelte_app/package.json
svelte_web_components/svelte_app/project_package.json
svelte_web_components/svelte_app/vite.config.mjs
svelte_web_components-0.0.32.dist-info/LICENSE
svelte_web_components-0.0.32.dist-info/METADATA
svelte_web_components-0.0.32.dist-info/WHEEL
svelte_web_components-0.0.32.dist-info/entry_points.txt
svelte_web_components-0.0.32.dist-info/top_level.txt
svelte_web_components-0.0.32.dist-info/RECORD
