Metadata-Version: 2.1
Name: svelte-web-components
Version: 0.0.32
Summary: Svelte web components for python
Home-page: https://github.com/panos-stavrianos/svelte_web_components
Author: Panos Stavrianos
Author-email: panos@orbitsystems.gr
License: MIT license
Keywords: svelte,web components,python,fastapi,flask
Requires-Python: >=3.6
License-File: LICENSE
Requires-Dist: requests
Requires-Dist: setuptools
Requires-Dist: click
Requires-Dist: sh
Requires-Dist: rich
Requires-Dist: watchfiles
Requires-Dist: fastapi
Requires-Dist: uvicorn
Requires-Dist: jinja2
Requires-Dist: starlette
Requires-Dist: dirhash
Requires-Dist: python-multipart
